llama_utils/__init__.py
llama_utils/indexing/__init__.py
llama_utils/indexing/custom_index.py
llama_utils/indexing/index_manager.py
llama_utils/retrieval/__init__.py
llama_utils/retrieval/storage.py
llama_utils/utils/__init__.py
llama_utils/utils/config_loader.py
llama_utils/utils/errors.py
llama_utils/utils/helper_functions.py
llama_utils/utils/logger.py
llama_utils/utils/models.py
llama_utils-0.3.0.dist-info/LICENSE
llama_utils-0.3.0.dist-info/METADATA
llama_utils-0.3.0.dist-info/WHEEL
llama_utils-0.3.0.dist-info/RECORD
