Metadata-Version: 2.3
Name: llama-utils
Version: 0.3.0
Summary: LLM utilities for the Llama project
Keywords: llm,generativeai,chatbot,rag,natural language processing
Author: Mostafa Farrag
Author-email: moah.farag@gmail.com
Requires-Python: >=3.12,<4.0
Classifier: Programming Language :: Python :: 3
Classifier: Programming Language :: Python :: 3.12
Classifier: Programming Language :: Python :: 3.13
Requires-Dist: llama-index (>=0.12.12,<0.13.0)
Requires-Dist: pandas (>=2.2.3,<3.0.0)
